pygeon/__init__.py
pygeon/pygeonmethods.py
pygeon_notifications-1.0.2.dist-info/LICENSE
pygeon_notifications-1.0.2.dist-info/METADATA
pygeon_notifications-1.0.2.dist-info/WHEEL
pygeon_notifications-1.0.2.dist-info/entry_points.txt
pygeon_notifications-1.0.2.dist-info/top_level.txt
pygeon_notifications-1.0.2.dist-info/RECORD
