Metadata-Version: 2.1
Name: pygeon-notifications
Version: 1.0.2
Summary: Supplementary package for usage with Pygeon mobile application
Home-page: https://pygeon.io
Author: Azuth Technologies
Author-email: contact@pygeon.io
Classifier: Programming Language :: Python :: 3
Classifier: License :: OSI Approved :: MIT License
Classifier: Operating System :: OS Independent
Requires-Python: >=3.6
License-File: LICENSE
Requires-Dist: requests
